githubclitool/__init__.py
githubclitool/cli.py
githubclitool/github.py
githubclitool/secretscanner.py
githubclitool/tokenstore.py
githubclitool/utils.py
githubclitool-1.0.2.dist-info/METADATA
githubclitool-1.0.2.dist-info/WHEEL
githubclitool-1.0.2.dist-info/entry_points.txt
githubclitool-1.0.2.dist-info/top_level.txt
githubclitool-1.0.2.dist-info/RECORD
